matrix2str/__init__.py
matrix2str/main.py
matrix2str-1.0.0.dist-info/METADATA
matrix2str-1.0.0.dist-info/WHEEL
matrix2str-1.0.0.dist-info/licenses/LICENSE
matrix2str-1.0.0.dist-info/RECORD
